package com.baidu.mobstat;

import android.content.Context;
import android.content.Intent;
import com.baidu.bottom.service.BottomReceiver;

public class at
  extends Thread
{
  public at(BottomReceiver paramBottomReceiver, Context paramContext, Intent paramIntent, db paramdb) {}
  
  /* Error */
  public void run()
  {
    // Byte code:
    //   0: aload_0
    //   1: getfield 16	com/baidu/mobstat/at:d	Lcom/baidu/bottom/service/BottomReceiver;
    //   4: aload_0
    //   5: getfield 18	com/baidu/mobstat/at:a	Landroid/content/Context;
    //   8: aload_0
    //   9: getfield 20	com/baidu/mobstat/at:b	Landroid/content/Intent;
    //   12: invokestatic 33	com/baidu/bottom/service/BottomReceiver:a	(Lcom/baidu/bottom/service/BottomReceiver;Landroid/content/Context;Landroid/content/Intent;)V
    //   15: aload_0
    //   16: getfield 16	com/baidu/mobstat/at:d	Lcom/baidu/bottom/service/BottomReceiver;
    //   19: aload_0
    //   20: getfield 18	com/baidu/mobstat/at:a	Landroid/content/Context;
    //   23: aload_0
    //   24: getfield 20	com/baidu/mobstat/at:b	Landroid/content/Intent;
    //   27: invokestatic 35	com/baidu/bottom/service/BottomReceiver:b	(Lcom/baidu/bottom/service/BottomReceiver;Landroid/content/Context;Landroid/content/Intent;)V
    //   30: invokestatic 41	java/lang/System:currentTimeMillis	()J
    //   33: lstore 4
    //   35: lload 4
    //   37: invokestatic 43	com/baidu/bottom/service/BottomReceiver:a	()J
    //   40: lsub
    //   41: ldc2_w 44
    //   44: lcmp
    //   45: ifge +21 -> 66
    //   48: ldc 47
    //   50: invokestatic 52	com/baidu/mobstat/bd:a	(Ljava/lang/String;)V
    //   53: aload_0
    //   54: getfield 22	com/baidu/mobstat/at:c	Lcom/baidu/mobstat/db;
    //   57: invokevirtual 56	com/baidu/mobstat/db:b	()V
    //   60: aconst_null
    //   61: invokestatic 59	com/baidu/bottom/service/BottomReceiver:a	(Lcom/baidu/mobstat/db;)Lcom/baidu/mobstat/db;
    //   64: pop
    //   65: return
    //   66: lload 4
    //   68: invokestatic 62	com/baidu/bottom/service/BottomReceiver:a	(J)J
    //   71: pop2
    //   72: getstatic 67	com/baidu/mobstat/ao:c	Lcom/baidu/mobstat/ao;
    //   75: aload_0
    //   76: getfield 18	com/baidu/mobstat/at:a	Landroid/content/Context;
    //   79: invokevirtual 70	com/baidu/mobstat/ao:a	(Landroid/content/Context;)V
    //   82: goto +18 -> 100
    //   85: astore_2
    //   86: aload_0
    //   87: getfield 22	com/baidu/mobstat/at:c	Lcom/baidu/mobstat/db;
    //   90: invokevirtual 56	com/baidu/mobstat/db:b	()V
    //   93: aconst_null
    //   94: invokestatic 59	com/baidu/bottom/service/BottomReceiver:a	(Lcom/baidu/mobstat/db;)Lcom/baidu/mobstat/db;
    //   97: pop
    //   98: aload_2
    //   99: athrow
    //   100: aload_0
    //   101: getfield 22	com/baidu/mobstat/at:c	Lcom/baidu/mobstat/db;
    //   104: invokevirtual 56	com/baidu/mobstat/db:b	()V
    //   107: aconst_null
    //   108: invokestatic 59	com/baidu/bottom/service/BottomReceiver:a	(Lcom/baidu/mobstat/db;)Lcom/baidu/mobstat/db;
    //   111: pop
    //   112: return
    // Local variable table:
    //   start	length	slot	name	signature
    //   0	113	0	this	at
    //   85	14	2	localObject	Object
    //   100	1	3	localThrowable	Throwable
    //   33	34	4	l	long
    // Exception table:
    //   from	to	target	type
    //   0	53	85	finally
    //   66	82	85	finally
    //   0	53	100	java/lang/Throwable
    //   66	82	100	java/lang/Throwable
  }
}


/* Location:              E:\程序\作业\送给最好的TA_dex2jar.jar!\com\baidu\mobstat\at.class
 * Java compiler version: 6 (50.0)
 * JD-Core Version:       0.7.1
 */