package com.baidu.mobstat;

import android.content.Context;
import org.json.JSONObject;

class bu
{
  static String a = "Android";
  boolean b = false;
  String c;
  String d;
  String e = "0";
  String f = null;
  String g = null;
  int h = -1;
  String i;
  String j;
  int k;
  int l;
  String m = null;
  String n;
  String o;
  String p;
  String q;
  String r;
  String s;
  String t;
  String u;
  String v;
  String w;
  String x;
  JSONObject y;
  int z = 0;
  
  /* Error */
  public void a(Context paramContext)
  {
    // Byte code:
    //   0: aload_0
    //   1: monitorenter
    //   2: aload_0
    //   3: getfield 43	com/baidu/mobstat/bu:b	Z
    //   6: istore_3
    //   7: iload_3
    //   8: ifeq +6 -> 14
    //   11: aload_0
    //   12: monitorexit
    //   13: return
    //   14: aload_1
    //   15: ldc 62
    //   17: invokestatic 67	com/baidu/mobstat/cs:e	(Landroid/content/Context;Ljava/lang/String;)Z
    //   20: pop
    //   21: aload_1
    //   22: ldc 69
    //   24: invokestatic 67	com/baidu/mobstat/cs:e	(Landroid/content/Context;Ljava/lang/String;)Z
    //   27: pop
    //   28: aload_1
    //   29: ldc 71
    //   31: invokestatic 67	com/baidu/mobstat/cs:e	(Landroid/content/Context;Ljava/lang/String;)Z
    //   34: pop
    //   35: aload_1
    //   36: ldc 73
    //   38: invokestatic 67	com/baidu/mobstat/cs:e	(Landroid/content/Context;Ljava/lang/String;)Z
    //   41: pop
    //   42: aload_1
    //   43: ldc 75
    //   45: invokevirtual 81	android/content/Context:getSystemService	(Ljava/lang/String;)Ljava/lang/Object;
    //   48: checkcast 83	android/telephony/TelephonyManager
    //   51: astore 8
    //   53: aload_0
    //   54: invokestatic 88	com/baidu/mobstat/CooperService:a	()Lcom/baidu/mobstat/CooperService;
    //   57: invokevirtual 92	com/baidu/mobstat/CooperService:getOSVersion	()Ljava/lang/String;
    //   60: putfield 94	com/baidu/mobstat/bu:c	Ljava/lang/String;
    //   63: aload_0
    //   64: invokestatic 88	com/baidu/mobstat/CooperService:a	()Lcom/baidu/mobstat/CooperService;
    //   67: invokevirtual 97	com/baidu/mobstat/CooperService:getOSSysVersion	()Ljava/lang/String;
    //   70: putfield 99	com/baidu/mobstat/bu:d	Ljava/lang/String;
    //   73: aload_0
    //   74: invokestatic 88	com/baidu/mobstat/CooperService:a	()Lcom/baidu/mobstat/CooperService;
    //   77: invokevirtual 102	com/baidu/mobstat/CooperService:getPhoneModel	()Ljava/lang/String;
    //   80: putfield 104	com/baidu/mobstat/bu:o	Ljava/lang/String;
    //   83: aload_0
    //   84: invokestatic 88	com/baidu/mobstat/CooperService:a	()Lcom/baidu/mobstat/CooperService;
    //   87: invokevirtual 107	com/baidu/mobstat/CooperService:getManufacturer	()Ljava/lang/String;
    //   90: putfield 109	com/baidu/mobstat/bu:p	Ljava/lang/String;
    //   93: aload_0
    //   94: invokestatic 88	com/baidu/mobstat/CooperService:a	()Lcom/baidu/mobstat/CooperService;
    //   97: invokevirtual 112	com/baidu/mobstat/CooperService:getUUID	()Ljava/lang/String;
    //   100: putfield 114	com/baidu/mobstat/bu:x	Ljava/lang/String;
    //   103: aload_0
    //   104: invokestatic 88	com/baidu/mobstat/CooperService:a	()Lcom/baidu/mobstat/CooperService;
    //   107: aload_1
    //   108: invokevirtual 118	com/baidu/mobstat/CooperService:getHeaderExt	(Landroid/content/Context;)Lorg/json/JSONObject;
    //   111: putfield 120	com/baidu/mobstat/bu:y	Lorg/json/JSONObject;
    //   114: aload_0
    //   115: invokestatic 88	com/baidu/mobstat/CooperService:a	()Lcom/baidu/mobstat/CooperService;
    //   118: aload 8
    //   120: aload_1
    //   121: invokevirtual 124	com/baidu/mobstat/CooperService:getDeviceId	(Landroid/telephony/TelephonyManager;Landroid/content/Context;)Ljava/lang/String;
    //   124: putfield 126	com/baidu/mobstat/bu:j	Ljava/lang/String;
    //   127: invokestatic 131	com/baidu/mobstat/bj:a	()Lcom/baidu/mobstat/bj;
    //   130: aload_1
    //   131: invokevirtual 134	com/baidu/mobstat/bj:i	(Landroid/content/Context;)Z
    //   134: ifeq +414 -> 548
    //   137: ldc -120
    //   139: astore 9
    //   141: goto +3 -> 144
    //   144: aload_0
    //   145: aload 9
    //   147: putfield 47	com/baidu/mobstat/bu:e	Ljava/lang/String;
    //   150: aload_1
    //   151: invokestatic 140	com/baidu/mobstat/dc:s	(Landroid/content/Context;)Z
    //   154: ifeq +9 -> 163
    //   157: aload_0
    //   158: ldc -114
    //   160: putfield 47	com/baidu/mobstat/bu:e	Ljava/lang/String;
    //   163: new 144	java/lang/StringBuilder
    //   166: dup
    //   167: invokespecial 145	java/lang/StringBuilder:<init>	()V
    //   170: astore 10
    //   172: aload 10
    //   174: aload_0
    //   175: getfield 47	com/baidu/mobstat/bu:e	Ljava/lang/String;
    //   178: invokevirtual 149	java/lang/StringBuilder:append	(Ljava/lang/String;)Ljava/lang/StringBuilder;
    //   181: pop
    //   182: aload 10
    //   184: ldc -105
    //   186: invokevirtual 149	java/lang/StringBuilder:append	(Ljava/lang/String;)Ljava/lang/StringBuilder;
    //   189: pop
    //   190: aload_0
    //   191: aload 10
    //   193: invokevirtual 154	java/lang/StringBuilder:toString	()Ljava/lang/String;
    //   196: putfield 47	com/baidu/mobstat/bu:e	Ljava/lang/String;
    //   199: invokestatic 88	com/baidu/mobstat/CooperService:a	()Lcom/baidu/mobstat/CooperService;
    //   202: aload_1
    //   203: invokevirtual 157	com/baidu/mobstat/CooperService:isDeviceMacEnabled	(Landroid/content/Context;)Z
    //   206: istore 24
    //   208: aload_0
    //   209: invokestatic 88	com/baidu/mobstat/CooperService:a	()Lcom/baidu/mobstat/CooperService;
    //   212: aload_1
    //   213: iload 24
    //   215: invokevirtual 161	com/baidu/mobstat/CooperService:getMacAddress	(Landroid/content/Context;Z)Ljava/lang/String;
    //   218: putfield 163	com/baidu/mobstat/bu:t	Ljava/lang/String;
    //   221: goto +10 -> 231
    //   224: astore 13
    //   226: aload 13
    //   228: invokestatic 168	com/baidu/mobstat/cz:a	(Ljava/lang/Throwable;)V
    //   231: aload_0
    //   232: iconst_1
    //   233: aload_1
    //   234: invokestatic 171	com/baidu/mobstat/dc:f	(ILandroid/content/Context;)Ljava/lang/String;
    //   237: putfield 173	com/baidu/mobstat/bu:v	Ljava/lang/String;
    //   240: goto +10 -> 250
    //   243: astore 14
    //   245: aload 14
    //   247: invokestatic 168	com/baidu/mobstat/cz:a	(Ljava/lang/Throwable;)V
    //   250: aload_0
    //   251: aload_1
    //   252: iconst_1
    //   253: invokestatic 176	com/baidu/mobstat/dc:a	(Landroid/content/Context;I)Ljava/lang/String;
    //   256: putfield 178	com/baidu/mobstat/bu:w	Ljava/lang/String;
    //   259: goto +10 -> 269
    //   262: astore 15
    //   264: aload 15
    //   266: invokestatic 168	com/baidu/mobstat/cz:a	(Ljava/lang/Throwable;)V
    //   269: aload_0
    //   270: invokestatic 88	com/baidu/mobstat/CooperService:a	()Lcom/baidu/mobstat/CooperService;
    //   273: aload_1
    //   274: iconst_1
    //   275: invokevirtual 181	com/baidu/mobstat/CooperService:getCUID	(Landroid/content/Context;Z)Ljava/lang/String;
    //   278: putfield 51	com/baidu/mobstat/bu:g	Ljava/lang/String;
    //   281: aload_0
    //   282: invokestatic 88	com/baidu/mobstat/CooperService:a	()Lcom/baidu/mobstat/CooperService;
    //   285: aload 8
    //   287: invokevirtual 185	com/baidu/mobstat/CooperService:getOperator	(Landroid/telephony/TelephonyManager;)Ljava/lang/String;
    //   290: putfield 187	com/baidu/mobstat/bu:n	Ljava/lang/String;
    //   293: goto +10 -> 303
    //   296: astore 16
    //   298: aload 16
    //   300: invokestatic 168	com/baidu/mobstat/cz:a	(Ljava/lang/Throwable;)V
    //   303: aload_0
    //   304: aload_1
    //   305: invokestatic 190	com/baidu/mobstat/dc:b	(Landroid/content/Context;)I
    //   308: putfield 192	com/baidu/mobstat/bu:k	I
    //   311: aload_0
    //   312: aload_1
    //   313: invokestatic 194	com/baidu/mobstat/dc:c	(Landroid/content/Context;)I
    //   316: putfield 196	com/baidu/mobstat/bu:l	I
    //   319: aload_1
    //   320: invokevirtual 200	android/content/Context:getResources	()Landroid/content/res/Resources;
    //   323: invokevirtual 206	android/content/res/Resources:getConfiguration	()Landroid/content/res/Configuration;
    //   326: getfield 211	android/content/res/Configuration:orientation	I
    //   329: iconst_2
    //   330: if_icmpne +52 -> 382
    //   333: aload_0
    //   334: aload_0
    //   335: getfield 192	com/baidu/mobstat/bu:k	I
    //   338: aload_0
    //   339: getfield 196	com/baidu/mobstat/bu:l	I
    //   342: ixor
    //   343: putfield 192	com/baidu/mobstat/bu:k	I
    //   346: aload_0
    //   347: aload_0
    //   348: getfield 192	com/baidu/mobstat/bu:k	I
    //   351: aload_0
    //   352: getfield 196	com/baidu/mobstat/bu:l	I
    //   355: ixor
    //   356: putfield 196	com/baidu/mobstat/bu:l	I
    //   359: aload_0
    //   360: aload_0
    //   361: getfield 192	com/baidu/mobstat/bu:k	I
    //   364: aload_0
    //   365: getfield 196	com/baidu/mobstat/bu:l	I
    //   368: ixor
    //   369: putfield 192	com/baidu/mobstat/bu:k	I
    //   372: goto +10 -> 382
    //   375: astore 17
    //   377: aload 17
    //   379: invokestatic 168	com/baidu/mobstat/cz:a	(Ljava/lang/Throwable;)V
    //   382: aload_0
    //   383: invokestatic 88	com/baidu/mobstat/CooperService:a	()Lcom/baidu/mobstat/CooperService;
    //   386: aload_1
    //   387: invokevirtual 215	com/baidu/mobstat/CooperService:getAppChannel	(Landroid/content/Context;)Ljava/lang/String;
    //   390: putfield 55	com/baidu/mobstat/bu:m	Ljava/lang/String;
    //   393: aload_0
    //   394: invokestatic 88	com/baidu/mobstat/CooperService:a	()Lcom/baidu/mobstat/CooperService;
    //   397: aload_1
    //   398: invokevirtual 218	com/baidu/mobstat/CooperService:getAppKey	(Landroid/content/Context;)Ljava/lang/String;
    //   401: putfield 49	com/baidu/mobstat/bu:f	Ljava/lang/String;
    //   404: aload_0
    //   405: invokestatic 88	com/baidu/mobstat/CooperService:a	()Lcom/baidu/mobstat/CooperService;
    //   408: aload_1
    //   409: invokevirtual 221	com/baidu/mobstat/CooperService:getAppVersionCode	(Landroid/content/Context;)I
    //   412: putfield 53	com/baidu/mobstat/bu:h	I
    //   415: aload_0
    //   416: invokestatic 88	com/baidu/mobstat/CooperService:a	()Lcom/baidu/mobstat/CooperService;
    //   419: aload_1
    //   420: invokevirtual 224	com/baidu/mobstat/CooperService:getAppVersionName	(Landroid/content/Context;)Ljava/lang/String;
    //   423: putfield 226	com/baidu/mobstat/bu:i	Ljava/lang/String;
    //   426: goto +10 -> 436
    //   429: astore 18
    //   431: aload 18
    //   433: invokestatic 168	com/baidu/mobstat/cz:a	(Ljava/lang/Throwable;)V
    //   436: invokestatic 88	com/baidu/mobstat/CooperService:a	()Lcom/baidu/mobstat/CooperService;
    //   439: aload_1
    //   440: invokevirtual 229	com/baidu/mobstat/CooperService:checkCellLocationSetting	(Landroid/content/Context;)Z
    //   443: ifeq +18 -> 461
    //   446: aload_1
    //   447: invokestatic 231	com/baidu/mobstat/dc:g	(Landroid/content/Context;)Ljava/lang/String;
    //   450: astore 23
    //   452: aload_0
    //   453: aload 23
    //   455: putfield 233	com/baidu/mobstat/bu:q	Ljava/lang/String;
    //   458: goto +17 -> 475
    //   461: ldc -21
    //   463: astore 23
    //   465: goto -13 -> 452
    //   468: astore 19
    //   470: aload 19
    //   472: invokestatic 168	com/baidu/mobstat/cz:a	(Ljava/lang/Throwable;)V
    //   475: invokestatic 88	com/baidu/mobstat/CooperService:a	()Lcom/baidu/mobstat/CooperService;
    //   478: aload_1
    //   479: invokevirtual 238	com/baidu/mobstat/CooperService:checkGPSLocationSetting	(Landroid/content/Context;)Z
    //   482: ifeq +18 -> 500
    //   485: aload_1
    //   486: invokestatic 240	com/baidu/mobstat/dc:h	(Landroid/content/Context;)Ljava/lang/String;
    //   489: astore 22
    //   491: aload_0
    //   492: aload 22
    //   494: putfield 242	com/baidu/mobstat/bu:r	Ljava/lang/String;
    //   497: goto +17 -> 514
    //   500: ldc -12
    //   502: astore 22
    //   504: goto -13 -> 491
    //   507: astore 20
    //   509: aload 20
    //   511: invokestatic 168	com/baidu/mobstat/cz:a	(Ljava/lang/Throwable;)V
    //   514: aload_0
    //   515: invokestatic 88	com/baidu/mobstat/CooperService:a	()Lcom/baidu/mobstat/CooperService;
    //   518: aload_1
    //   519: invokevirtual 247	com/baidu/mobstat/CooperService:getLinkedWay	(Landroid/content/Context;)Ljava/lang/String;
    //   522: putfield 249	com/baidu/mobstat/bu:s	Ljava/lang/String;
    //   525: goto +10 -> 535
    //   528: astore 21
    //   530: aload 21
    //   532: invokestatic 168	com/baidu/mobstat/cz:a	(Ljava/lang/Throwable;)V
    //   535: aload_0
    //   536: iconst_1
    //   537: putfield 43	com/baidu/mobstat/bu:b	Z
    //   540: aload_0
    //   541: monitorexit
    //   542: return
    //   543: astore_2
    //   544: aload_0
    //   545: monitorexit
    //   546: aload_2
    //   547: athrow
    //   548: ldc 45
    //   550: astore 9
    //   552: goto -408 -> 144
    // Local variable table:
    //   start	length	slot	name	signature
    //   0	555	0	this	bu
    //   0	555	1	paramContext	Context
    //   543	4	2	localObject	Object
    //   6	2	3	bool1	boolean
    //   51	235	8	localTelephonyManager	android.telephony.TelephonyManager
    //   139	412	9	str1	String
    //   170	22	10	localStringBuilder	StringBuilder
    //   224	3	13	localException1	Exception
    //   243	3	14	localException2	Exception
    //   262	3	15	localException3	Exception
    //   296	3	16	localException4	Exception
    //   375	3	17	localException5	Exception
    //   429	3	18	localException6	Exception
    //   468	3	19	localException7	Exception
    //   507	3	20	localException8	Exception
    //   528	3	21	localException9	Exception
    //   489	14	22	str2	String
    //   450	14	23	str3	String
    //   206	8	24	bool2	boolean
    // Exception table:
    //   from	to	target	type
    //   199	221	224	java/lang/Exception
    //   231	240	243	java/lang/Exception
    //   250	259	262	java/lang/Exception
    //   281	293	296	java/lang/Exception
    //   303	372	375	java/lang/Exception
    //   404	426	429	java/lang/Exception
    //   436	452	468	java/lang/Exception
    //   452	458	468	java/lang/Exception
    //   475	491	507	java/lang/Exception
    //   491	497	507	java/lang/Exception
    //   514	525	528	java/lang/Exception
    //   2	7	543	finally
    //   14	137	543	finally
    //   144	163	543	finally
    //   163	199	543	finally
    //   199	221	543	finally
    //   226	231	543	finally
    //   231	240	543	finally
    //   245	250	543	finally
    //   250	259	543	finally
    //   264	269	543	finally
    //   269	281	543	finally
    //   281	293	543	finally
    //   298	303	543	finally
    //   303	372	543	finally
    //   377	382	543	finally
    //   382	404	543	finally
    //   404	426	543	finally
    //   431	436	543	finally
    //   436	452	543	finally
    //   452	458	543	finally
    //   470	475	543	finally
    //   475	491	543	finally
    //   491	497	543	finally
    //   509	514	543	finally
    //   514	525	543	finally
    //   530	535	543	finally
    //   535	540	543	finally
  }
  
  public void a(Context paramContext, JSONObject paramJSONObject)
  {
    try
    {
      a(paramContext);
      if (paramJSONObject.length() > 10)
      {
        StringBuilder localStringBuilder = new StringBuilder();
        localStringBuilder.append("header has been installed; header is:");
        localStringBuilder.append(paramJSONObject);
        cz.a(localStringBuilder.toString());
        return;
      }
      b(paramContext, paramJSONObject);
      return;
    }
    finally {}
  }
  
  public void a(JSONObject paramJSONObject)
  {
    this.y = paramJSONObject;
  }
  
  /* Error */
  public void b(Context paramContext, JSONObject paramJSONObject)
  {
    // Byte code:
    //   0: aload_0
    //   1: monitorenter
    //   2: getstatic 273	com/baidu/mobstat/bu:a	Ljava/lang/String;
    //   5: ifnonnull +10 -> 15
    //   8: ldc -12
    //   10: astore 4
    //   12: goto +8 -> 20
    //   15: getstatic 273	com/baidu/mobstat/bu:a	Ljava/lang/String;
    //   18: astore 4
    //   20: aload_2
    //   21: ldc_w 274
    //   24: aload 4
    //   26: invokevirtual 278	org/json/JSONObject:put	(Ljava/lang/String;Ljava/lang/Object;)Lorg/json/JSONObject;
    //   29: pop
    //   30: aload_2
    //   31: ldc_w 280
    //   34: iconst_0
    //   35: invokevirtual 283	org/json/JSONObject:put	(Ljava/lang/String;I)Lorg/json/JSONObject;
    //   38: pop
    //   39: aload_0
    //   40: getfield 94	com/baidu/mobstat/bu:c	Ljava/lang/String;
    //   43: ifnonnull +10 -> 53
    //   46: ldc -12
    //   48: astore 7
    //   50: goto +9 -> 59
    //   53: aload_0
    //   54: getfield 94	com/baidu/mobstat/bu:c	Ljava/lang/String;
    //   57: astore 7
    //   59: aload_2
    //   60: ldc_w 284
    //   63: aload 7
    //   65: invokevirtual 278	org/json/JSONObject:put	(Ljava/lang/String;Ljava/lang/Object;)Lorg/json/JSONObject;
    //   68: pop
    //   69: aload_0
    //   70: getfield 99	com/baidu/mobstat/bu:d	Ljava/lang/String;
    //   73: ifnonnull +10 -> 83
    //   76: ldc -12
    //   78: astore 9
    //   80: goto +9 -> 89
    //   83: aload_0
    //   84: getfield 99	com/baidu/mobstat/bu:d	Ljava/lang/String;
    //   87: astore 9
    //   89: aload_2
    //   90: ldc_w 286
    //   93: aload 9
    //   95: invokevirtual 278	org/json/JSONObject:put	(Ljava/lang/String;Ljava/lang/Object;)Lorg/json/JSONObject;
    //   98: pop
    //   99: aload_0
    //   100: getfield 49	com/baidu/mobstat/bu:f	Ljava/lang/String;
    //   103: ifnonnull +10 -> 113
    //   106: ldc -12
    //   108: astore 11
    //   110: goto +9 -> 119
    //   113: aload_0
    //   114: getfield 49	com/baidu/mobstat/bu:f	Ljava/lang/String;
    //   117: astore 11
    //   119: aload_2
    //   120: ldc_w 287
    //   123: aload 11
    //   125: invokevirtual 278	org/json/JSONObject:put	(Ljava/lang/String;Ljava/lang/Object;)Lorg/json/JSONObject;
    //   128: pop
    //   129: aload_0
    //   130: getfield 47	com/baidu/mobstat/bu:e	Ljava/lang/String;
    //   133: ifnonnull +10 -> 143
    //   136: ldc 45
    //   138: astore 13
    //   140: goto +9 -> 149
    //   143: aload_0
    //   144: getfield 47	com/baidu/mobstat/bu:e	Ljava/lang/String;
    //   147: astore 13
    //   149: aload_2
    //   150: ldc_w 289
    //   153: aload 13
    //   155: invokevirtual 278	org/json/JSONObject:put	(Ljava/lang/String;Ljava/lang/Object;)Lorg/json/JSONObject;
    //   158: pop
    //   159: aload_2
    //   160: ldc_w 290
    //   163: ldc -12
    //   165: invokevirtual 278	org/json/JSONObject:put	(Ljava/lang/String;Ljava/lang/Object;)Lorg/json/JSONObject;
    //   168: pop
    //   169: aload_2
    //   170: ldc_w 291
    //   173: ldc_w 293
    //   176: invokevirtual 278	org/json/JSONObject:put	(Ljava/lang/String;Ljava/lang/Object;)Lorg/json/JSONObject;
    //   179: pop
    //   180: aload_2
    //   181: ldc_w 295
    //   184: iconst_0
    //   185: invokevirtual 283	org/json/JSONObject:put	(Ljava/lang/String;I)Lorg/json/JSONObject;
    //   188: pop
    //   189: aload_2
    //   190: ldc_w 296
    //   193: aload_0
    //   194: getfield 53	com/baidu/mobstat/bu:h	I
    //   197: invokevirtual 283	org/json/JSONObject:put	(Ljava/lang/String;I)Lorg/json/JSONObject;
    //   200: pop
    //   201: aload_0
    //   202: getfield 226	com/baidu/mobstat/bu:i	Ljava/lang/String;
    //   205: ifnonnull +10 -> 215
    //   208: ldc -12
    //   210: astore 19
    //   212: goto +9 -> 221
    //   215: aload_0
    //   216: getfield 226	com/baidu/mobstat/bu:i	Ljava/lang/String;
    //   219: astore 19
    //   221: aload_2
    //   222: ldc_w 297
    //   225: aload 19
    //   227: invokevirtual 278	org/json/JSONObject:put	(Ljava/lang/String;Ljava/lang/Object;)Lorg/json/JSONObject;
    //   230: pop
    //   231: aload_2
    //   232: ldc_w 298
    //   235: ldc -12
    //   237: invokevirtual 278	org/json/JSONObject:put	(Ljava/lang/String;Ljava/lang/Object;)Lorg/json/JSONObject;
    //   240: pop
    //   241: aload_0
    //   242: getfield 163	com/baidu/mobstat/bu:t	Ljava/lang/String;
    //   245: ifnonnull +10 -> 255
    //   248: ldc -12
    //   250: astore 22
    //   252: goto +9 -> 261
    //   255: aload_0
    //   256: getfield 163	com/baidu/mobstat/bu:t	Ljava/lang/String;
    //   259: astore 22
    //   261: aload_2
    //   262: ldc_w 300
    //   265: aload 22
    //   267: invokevirtual 278	org/json/JSONObject:put	(Ljava/lang/String;Ljava/lang/Object;)Lorg/json/JSONObject;
    //   270: pop
    //   271: aload_0
    //   272: getfield 173	com/baidu/mobstat/bu:v	Ljava/lang/String;
    //   275: ifnonnull +10 -> 285
    //   278: ldc -12
    //   280: astore 24
    //   282: goto +9 -> 291
    //   285: aload_0
    //   286: getfield 173	com/baidu/mobstat/bu:v	Ljava/lang/String;
    //   289: astore 24
    //   291: aload_2
    //   292: ldc_w 302
    //   295: aload 24
    //   297: invokevirtual 278	org/json/JSONObject:put	(Ljava/lang/String;Ljava/lang/Object;)Lorg/json/JSONObject;
    //   300: pop
    //   301: aload_0
    //   302: getfield 126	com/baidu/mobstat/bu:j	Ljava/lang/String;
    //   305: ifnonnull +10 -> 315
    //   308: ldc -12
    //   310: astore 26
    //   312: goto +9 -> 321
    //   315: aload_0
    //   316: getfield 126	com/baidu/mobstat/bu:j	Ljava/lang/String;
    //   319: astore 26
    //   321: aload_2
    //   322: ldc_w 304
    //   325: aload 26
    //   327: invokevirtual 278	org/json/JSONObject:put	(Ljava/lang/String;Ljava/lang/Object;)Lorg/json/JSONObject;
    //   330: pop
    //   331: aload_0
    //   332: getfield 51	com/baidu/mobstat/bu:g	Ljava/lang/String;
    //   335: ifnonnull +10 -> 345
    //   338: ldc -12
    //   340: astore 28
    //   342: goto +9 -> 351
    //   345: aload_0
    //   346: getfield 51	com/baidu/mobstat/bu:g	Ljava/lang/String;
    //   349: astore 28
    //   351: aload_2
    //   352: ldc_w 306
    //   355: aload 28
    //   357: invokevirtual 278	org/json/JSONObject:put	(Ljava/lang/String;Ljava/lang/Object;)Lorg/json/JSONObject;
    //   360: pop
    //   361: aload_2
    //   362: ldc_w 308
    //   365: iconst_1
    //   366: invokevirtual 283	org/json/JSONObject:put	(Ljava/lang/String;I)Lorg/json/JSONObject;
    //   369: pop
    //   370: aload_2
    //   371: ldc_w 309
    //   374: aload_0
    //   375: getfield 192	com/baidu/mobstat/bu:k	I
    //   378: invokevirtual 283	org/json/JSONObject:put	(Ljava/lang/String;I)Lorg/json/JSONObject;
    //   381: pop
    //   382: aload_2
    //   383: ldc_w 310
    //   386: aload_0
    //   387: getfield 196	com/baidu/mobstat/bu:l	I
    //   390: invokevirtual 283	org/json/JSONObject:put	(Ljava/lang/String;I)Lorg/json/JSONObject;
    //   393: pop
    //   394: aload_0
    //   395: getfield 178	com/baidu/mobstat/bu:w	Ljava/lang/String;
    //   398: ifnonnull +10 -> 408
    //   401: ldc -12
    //   403: astore 33
    //   405: goto +9 -> 414
    //   408: aload_0
    //   409: getfield 178	com/baidu/mobstat/bu:w	Ljava/lang/String;
    //   412: astore 33
    //   414: aload_2
    //   415: ldc_w 312
    //   418: aload 33
    //   420: invokevirtual 278	org/json/JSONObject:put	(Ljava/lang/String;Ljava/lang/Object;)Lorg/json/JSONObject;
    //   423: pop
    //   424: aload_0
    //   425: getfield 55	com/baidu/mobstat/bu:m	Ljava/lang/String;
    //   428: ifnonnull +10 -> 438
    //   431: ldc -12
    //   433: astore 35
    //   435: goto +9 -> 444
    //   438: aload_0
    //   439: getfield 55	com/baidu/mobstat/bu:m	Ljava/lang/String;
    //   442: astore 35
    //   444: aload_2
    //   445: ldc_w 313
    //   448: aload 35
    //   450: invokevirtual 278	org/json/JSONObject:put	(Ljava/lang/String;Ljava/lang/Object;)Lorg/json/JSONObject;
    //   453: pop
    //   454: aload_0
    //   455: getfield 187	com/baidu/mobstat/bu:n	Ljava/lang/String;
    //   458: ifnonnull +10 -> 468
    //   461: ldc -12
    //   463: astore 37
    //   465: goto +9 -> 474
    //   468: aload_0
    //   469: getfield 187	com/baidu/mobstat/bu:n	Ljava/lang/String;
    //   472: astore 37
    //   474: aload_2
    //   475: ldc_w 315
    //   478: aload 37
    //   480: invokevirtual 278	org/json/JSONObject:put	(Ljava/lang/String;Ljava/lang/Object;)Lorg/json/JSONObject;
    //   483: pop
    //   484: aload_0
    //   485: getfield 104	com/baidu/mobstat/bu:o	Ljava/lang/String;
    //   488: ifnonnull +10 -> 498
    //   491: ldc -12
    //   493: astore 39
    //   495: goto +9 -> 504
    //   498: aload_0
    //   499: getfield 104	com/baidu/mobstat/bu:o	Ljava/lang/String;
    //   502: astore 39
    //   504: aload_2
    //   505: ldc_w 316
    //   508: aload 39
    //   510: invokevirtual 278	org/json/JSONObject:put	(Ljava/lang/String;Ljava/lang/Object;)Lorg/json/JSONObject;
    //   513: pop
    //   514: aload_0
    //   515: getfield 109	com/baidu/mobstat/bu:p	Ljava/lang/String;
    //   518: ifnonnull +10 -> 528
    //   521: ldc -12
    //   523: astore 41
    //   525: goto +9 -> 534
    //   528: aload_0
    //   529: getfield 109	com/baidu/mobstat/bu:p	Ljava/lang/String;
    //   532: astore 41
    //   534: aload_2
    //   535: ldc_w 318
    //   538: aload 41
    //   540: invokevirtual 278	org/json/JSONObject:put	(Ljava/lang/String;Ljava/lang/Object;)Lorg/json/JSONObject;
    //   543: pop
    //   544: aload_2
    //   545: ldc_w 320
    //   548: aload_0
    //   549: getfield 233	com/baidu/mobstat/bu:q	Ljava/lang/String;
    //   552: invokevirtual 278	org/json/JSONObject:put	(Ljava/lang/String;Ljava/lang/Object;)Lorg/json/JSONObject;
    //   555: pop
    //   556: aload_0
    //   557: getfield 242	com/baidu/mobstat/bu:r	Ljava/lang/String;
    //   560: ifnonnull +10 -> 570
    //   563: ldc -12
    //   565: astore 44
    //   567: goto +9 -> 576
    //   570: aload_0
    //   571: getfield 242	com/baidu/mobstat/bu:r	Ljava/lang/String;
    //   574: astore 44
    //   576: aload_2
    //   577: ldc_w 322
    //   580: aload 44
    //   582: invokevirtual 278	org/json/JSONObject:put	(Ljava/lang/String;Ljava/lang/Object;)Lorg/json/JSONObject;
    //   585: pop
    //   586: aload_0
    //   587: getfield 249	com/baidu/mobstat/bu:s	Ljava/lang/String;
    //   590: ifnonnull +10 -> 600
    //   593: ldc -12
    //   595: astore 46
    //   597: goto +9 -> 606
    //   600: aload_0
    //   601: getfield 249	com/baidu/mobstat/bu:s	Ljava/lang/String;
    //   604: astore 46
    //   606: aload_2
    //   607: ldc_w 323
    //   610: aload 46
    //   612: invokevirtual 278	org/json/JSONObject:put	(Ljava/lang/String;Ljava/lang/Object;)Lorg/json/JSONObject;
    //   615: pop
    //   616: aload_2
    //   617: ldc_w 324
    //   620: invokestatic 330	java/lang/System:currentTimeMillis	()J
    //   623: invokevirtual 333	org/json/JSONObject:put	(Ljava/lang/String;J)Lorg/json/JSONObject;
    //   626: pop
    //   627: aload_2
    //   628: ldc_w 335
    //   631: aload_0
    //   632: getfield 57	com/baidu/mobstat/bu:z	I
    //   635: invokevirtual 283	org/json/JSONObject:put	(Ljava/lang/String;I)Lorg/json/JSONObject;
    //   638: pop
    //   639: aload_2
    //   640: ldc_w 337
    //   643: iconst_1
    //   644: aload_1
    //   645: invokestatic 339	com/baidu/mobstat/dc:h	(ILandroid/content/Context;)Ljava/lang/String;
    //   648: invokevirtual 278	org/json/JSONObject:put	(Ljava/lang/String;Ljava/lang/Object;)Lorg/json/JSONObject;
    //   651: pop
    //   652: aload_1
    //   653: invokestatic 341	com/baidu/mobstat/dc:q	(Landroid/content/Context;)Ljava/lang/String;
    //   656: astore 51
    //   658: aload_2
    //   659: ldc_w 343
    //   662: aload 51
    //   664: invokevirtual 278	org/json/JSONObject:put	(Ljava/lang/String;Ljava/lang/Object;)Lorg/json/JSONObject;
    //   667: pop
    //   668: aload 51
    //   670: invokestatic 349	android/text/TextUtils:isEmpty	(Ljava/lang/CharSequence;)Z
    //   673: istore 53
    //   675: aconst_null
    //   676: astore 54
    //   678: iload 53
    //   680: ifne +156 -> 836
    //   683: aload_1
    //   684: invokestatic 351	com/baidu/mobstat/dc:r	(Landroid/content/Context;)Ljava/lang/String;
    //   687: astore 54
    //   689: goto +147 -> 836
    //   692: aload_2
    //   693: ldc_w 353
    //   696: aload 54
    //   698: invokevirtual 278	org/json/JSONObject:put	(Ljava/lang/String;Ljava/lang/Object;)Lorg/json/JSONObject;
    //   701: pop
    //   702: aload_0
    //   703: getfield 114	com/baidu/mobstat/bu:x	Ljava/lang/String;
    //   706: ifnonnull +10 -> 716
    //   709: ldc -12
    //   711: astore 56
    //   713: goto +9 -> 722
    //   716: aload_0
    //   717: getfield 114	com/baidu/mobstat/bu:x	Ljava/lang/String;
    //   720: astore 56
    //   722: aload_2
    //   723: ldc_w 355
    //   726: aload 56
    //   728: invokevirtual 278	org/json/JSONObject:put	(Ljava/lang/String;Ljava/lang/Object;)Lorg/json/JSONObject;
    //   731: pop
    //   732: aload_0
    //   733: getfield 120	com/baidu/mobstat/bu:y	Lorg/json/JSONObject;
    //   736: ifnull +25 -> 761
    //   739: aload_0
    //   740: getfield 120	com/baidu/mobstat/bu:y	Lorg/json/JSONObject;
    //   743: invokevirtual 258	org/json/JSONObject:length	()I
    //   746: ifeq +15 -> 761
    //   749: aload_2
    //   750: ldc_w 357
    //   753: aload_0
    //   754: getfield 120	com/baidu/mobstat/bu:y	Lorg/json/JSONObject;
    //   757: invokevirtual 278	org/json/JSONObject:put	(Ljava/lang/String;Ljava/lang/Object;)Lorg/json/JSONObject;
    //   760: pop
    //   761: new 144	java/lang/StringBuilder
    //   764: dup
    //   765: invokespecial 145	java/lang/StringBuilder:<init>	()V
    //   768: astore 58
    //   770: aload 58
    //   772: ldc_w 359
    //   775: invokevirtual 149	java/lang/StringBuilder:append	(Ljava/lang/String;)Ljava/lang/StringBuilder;
    //   778: pop
    //   779: aload 58
    //   781: aload_2
    //   782: invokevirtual 360	org/json/JSONObject:toString	()Ljava/lang/String;
    //   785: invokevirtual 149	java/lang/StringBuilder:append	(Ljava/lang/String;)Ljava/lang/StringBuilder;
    //   788: pop
    //   789: aload 58
    //   791: ldc_w 362
    //   794: invokevirtual 149	java/lang/StringBuilder:append	(Ljava/lang/String;)Ljava/lang/StringBuilder;
    //   797: pop
    //   798: aload 58
    //   800: aload_2
    //   801: invokevirtual 258	org/json/JSONObject:length	()I
    //   804: invokevirtual 365	java/lang/StringBuilder:append	(I)Ljava/lang/StringBuilder;
    //   807: pop
    //   808: aload 58
    //   810: invokevirtual 154	java/lang/StringBuilder:toString	()Ljava/lang/String;
    //   813: invokestatic 266	com/baidu/mobstat/cz:a	(Ljava/lang/String;)V
    //   816: goto +13 -> 829
    //   819: astore_3
    //   820: goto +12 -> 832
    //   823: ldc_w 367
    //   826: invokestatic 266	com/baidu/mobstat/cz:a	(Ljava/lang/String;)V
    //   829: aload_0
    //   830: monitorexit
    //   831: return
    //   832: aload_0
    //   833: monitorexit
    //   834: aload_3
    //   835: athrow
    //   836: aload 54
    //   838: ifnonnull -146 -> 692
    //   841: ldc -12
    //   843: astore 54
    //   845: goto -153 -> 692
    // Local variable table:
    //   start	length	slot	name	signature
    //   0	848	0	this	bu
    //   0	848	1	paramContext	Context
    //   0	848	2	paramJSONObject	JSONObject
    //   819	16	3	localObject	Object
    //   10	15	4	str1	String
    //   48	16	7	str2	String
    //   78	16	9	str3	String
    //   108	16	11	str4	String
    //   138	16	13	str5	String
    //   210	16	19	str6	String
    //   250	16	22	str7	String
    //   280	16	24	str8	String
    //   310	16	26	str9	String
    //   823	1	26	localJSONException	org.json.JSONException
    //   340	16	28	str10	String
    //   403	16	33	str11	String
    //   433	16	35	str12	String
    //   463	16	37	str13	String
    //   493	16	39	str14	String
    //   523	16	41	str15	String
    //   565	16	44	str16	String
    //   595	16	46	str17	String
    //   656	13	51	str18	String
    //   673	6	53	bool	boolean
    //   676	168	54	str19	String
    //   711	16	56	str20	String
    //   768	41	58	localStringBuilder	StringBuilder
    // Exception table:
    //   from	to	target	type
    //   2	8	819	finally
    //   15	20	819	finally
    //   20	46	819	finally
    //   53	59	819	finally
    //   59	76	819	finally
    //   83	89	819	finally
    //   89	106	819	finally
    //   113	119	819	finally
    //   119	136	819	finally
    //   143	149	819	finally
    //   149	208	819	finally
    //   215	221	819	finally
    //   221	248	819	finally
    //   255	261	819	finally
    //   261	278	819	finally
    //   285	291	819	finally
    //   291	308	819	finally
    //   315	321	819	finally
    //   321	338	819	finally
    //   345	351	819	finally
    //   351	401	819	finally
    //   408	414	819	finally
    //   414	431	819	finally
    //   438	444	819	finally
    //   444	461	819	finally
    //   468	474	819	finally
    //   474	491	819	finally
    //   498	504	819	finally
    //   504	521	819	finally
    //   528	534	819	finally
    //   534	563	819	finally
    //   570	576	819	finally
    //   576	593	819	finally
    //   600	606	819	finally
    //   606	675	819	finally
    //   683	689	819	finally
    //   692	709	819	finally
    //   716	722	819	finally
    //   722	761	819	finally
    //   761	816	819	finally
    //   823	829	819	finally
    //   2	8	823	org/json/JSONException
    //   15	20	823	org/json/JSONException
    //   20	46	823	org/json/JSONException
    //   53	59	823	org/json/JSONException
    //   59	76	823	org/json/JSONException
    //   83	89	823	org/json/JSONException
    //   89	106	823	org/json/JSONException
    //   113	119	823	org/json/JSONException
    //   119	136	823	org/json/JSONException
    //   143	149	823	org/json/JSONException
    //   149	208	823	org/json/JSONException
    //   215	221	823	org/json/JSONException
    //   221	248	823	org/json/JSONException
    //   255	261	823	org/json/JSONException
    //   261	278	823	org/json/JSONException
    //   285	291	823	org/json/JSONException
    //   291	308	823	org/json/JSONException
    //   315	321	823	org/json/JSONException
    //   321	338	823	org/json/JSONException
    //   345	351	823	org/json/JSONException
    //   351	401	823	org/json/JSONException
    //   408	414	823	org/json/JSONException
    //   414	431	823	org/json/JSONException
    //   438	444	823	org/json/JSONException
    //   444	461	823	org/json/JSONException
    //   468	474	823	org/json/JSONException
    //   474	491	823	org/json/JSONException
    //   498	504	823	org/json/JSONException
    //   504	521	823	org/json/JSONException
    //   528	534	823	org/json/JSONException
    //   534	563	823	org/json/JSONException
    //   570	576	823	org/json/JSONException
    //   576	593	823	org/json/JSONException
    //   600	606	823	org/json/JSONException
    //   606	675	823	org/json/JSONException
    //   683	689	823	org/json/JSONException
    //   692	709	823	org/json/JSONException
    //   716	722	823	org/json/JSONException
    //   722	761	823	org/json/JSONException
    //   761	816	823	org/json/JSONException
  }
}


/* Location:              E:\程序\作业\送给最好的TA_dex2jar.jar!\com\baidu\mobstat\bu.class
 * Java compiler version: 6 (50.0)
 * JD-Core Version:       0.7.1
 */